hcs_cli/__init__.py
hcs_cli/__main__.py
hcs_cli/main.py
hcs_cli/cmds/__init__.py
hcs_cli/cmds/api.py
hcs_cli/cmds/inspect.py
hcs_cli/cmds/login.py
hcs_cli/cmds/logout.py
hcs_cli/cmds/query.py
hcs_cli/cmds/task.py
hcs_cli/cmds/test.py
hcs_cli/cmds/upgrade.py
hcs_cli/cmds/ad/__init__.py
hcs_cli/cmds/ad/create.py
hcs_cli/cmds/ad/delete.py
hcs_cli/cmds/ad/get.py
hcs_cli/cmds/ad/list.py
hcs_cli/cmds/admin/__init__.py
hcs_cli/cmds/admin/azure_infra/__init__.py
hcs_cli/cmds/admin/azure_infra/main.py
hcs_cli/cmds/advisor/__init__.py
hcs_cli/cmds/advisor/advisor_utils.py
hcs_cli/cmds/advisor/html_utils.py
hcs_cli/cmds/advisor/org.py
hcs_cli/cmds/advisor/pdf_utils.py
hcs_cli/cmds/advisor/pool.py
hcs_cli/cmds/advisor/recommendation_engine.py
hcs_cli/cmds/advisor/config/__init__.py
hcs_cli/cmds/advisor/config/advisor_config.py
hcs_cli/cmds/app/__init__.py
hcs_cli/cmds/app/create.py
hcs_cli/cmds/app/delete.py
hcs_cli/cmds/app/get.py
hcs_cli/cmds/app/list.py
hcs_cli/cmds/app/update.py
hcs_cli/cmds/app/use.py
hcs_cli/cmds/auth/__init__.py
hcs_cli/cmds/auth/admin/__init__.py
hcs_cli/cmds/auth/admin/get_org_idp_map.py
hcs_cli/cmds/auth/admin/network/__init__.py
hcs_cli/cmds/auth/admin/network/add.py
hcs_cli/cmds/auth/user/__init__.py
hcs_cli/cmds/auth/user/list.py
hcs_cli/cmds/clouddriver/__init__.py
hcs_cli/cmds/clouddriver/provider.py
hcs_cli/cmds/clouddriver/summary.py
hcs_cli/cmds/clouddriver/task.py
hcs_cli/cmds/credential/__init__.py
hcs_cli/cmds/credential/get.py
hcs_cli/cmds/cs/__init__.py
hcs_cli/cmds/cs/base.py
hcs_cli/cmds/daas/__init__.py
hcs_cli/cmds/daas/infra/__init__.py
hcs_cli/cmds/daas/infra/basic.py
hcs_cli/cmds/daas/infra/plan.py
hcs_cli/cmds/daas/order/__init__.py
hcs_cli/cmds/daas/order/create.py
hcs_cli/cmds/daas/order/delete.py
hcs_cli/cmds/daas/order/list.py
hcs_cli/cmds/daas/order/update.py
hcs_cli/cmds/daas/tenant/__init__.py
hcs_cli/cmds/daas/tenant/consumption.py
hcs_cli/cmds/daas/tenant/create.py
hcs_cli/cmds/daas/tenant/plan.py
hcs_cli-0.1.321.dist-info/METADATA
hcs_cli-0.1.321.dist-info/WHEEL
hcs_cli-0.1.321.dist-info/entry_points.txt
hcs_cli-0.1.321.dist-info/RECORD
