Metadata-Version: 2.4
Name: hcs-cli
Version: 0.1.321
Summary: Horizon Cloud Service CLI.
Project-URL: Homepage, https://github.com/euc-eng/hcs-cli
Project-URL: Bug Tracker, https://github.com/euc-eng/hcs-cli/issues
Project-URL: documentation, https://readthedocs.org
Project-URL: repository, https://github.com/euc-eng/hcs-cli
Project-URL: changelog, https://github.com/euc-eng/hcs-cli/blob/main/CHANGELOG.md
Author-email: Nanw1103 <nanw1103@gmail.com>
Keywords: CLI,Horizon,Horizon Cloud,Horizon Cloud Service
Classifier: Development Status :: 3 - Alpha
Classifier: License :: OSI Approved :: MIT License
Classifier: Operating System :: OS Independent
Classifier: Programming Language :: Python :: 3
Requires-Python: >=3.9
Requires-Dist: hcs-core>=0.1.321
Requires-Dist: inquirerpy>=0.3.4
Requires-Dist: matplotlib>=3.8.0
Requires-Dist: paho-mqtt>=2.1.0
Requires-Dist: reportlab>=4.0.0
Provides-Extra: dev
Requires-Dist: bandit; extra == 'dev'
Requires-Dist: build; extra == 'dev'
Requires-Dist: flake8; extra == 'dev'
Requires-Dist: hatch; extra == 'dev'
Requires-Dist: mypy; extra == 'dev'
Requires-Dist: pylint; extra == 'dev'
Requires-Dist: pytest; extra == 'dev'
Requires-Dist: ruff; extra == 'dev'
Requires-Dist: twine; extra == 'dev'
Requires-Dist: vulture; extra == 'dev'
Requires-Dist: wheel; extra == 'dev'
Requires-Dist: yamlfix; extra == 'dev'
